napari_signal_selector/__init__.py
napari_signal_selector/_sample_data.py
napari_signal_selector/interactive.py
napari_signal_selector/line.py
napari_signal_selector/napari.yaml
napari_signal_selector/utilities.py
napari_signal_selector/_tests/__init__.py
napari_signal_selector/_tests/test_plotter.py
napari_signal_selector/_tests/test_sample_data.py
napari_signal_selector/icons/black/Back.png
napari_signal_selector/icons/black/Customize.png
napari_signal_selector/icons/black/Forward.png
napari_signal_selector/icons/black/Home.png
napari_signal_selector/icons/black/Pan.png
napari_signal_selector/icons/black/Pan_checked.png
napari_signal_selector/icons/black/Save.png
napari_signal_selector/icons/black/Subplots.png
napari_signal_selector/icons/black/Zoom.png
napari_signal_selector/icons/black/Zoom_checked.png
napari_signal_selector/icons/black/add_annotation.png
napari_signal_selector/icons/black/delete_annotation.png
napari_signal_selector/icons/black/hide_annotations.png
napari_signal_selector/icons/black/hide_predictions.png
napari_signal_selector/icons/black/hide_selected.png
napari_signal_selector/icons/black/select.png
napari_signal_selector/icons/black/select_checked.png
napari_signal_selector/icons/black/show_all.png
napari_signal_selector/icons/black/show_annotations.png
napari_signal_selector/icons/black/show_predictions.png
napari_signal_selector/icons/black/show_selected.png
napari_signal_selector/icons/black/span_select.png
napari_signal_selector/icons/black/span_select_checked.png
napari_signal_selector/icons/white/Back.png
napari_signal_selector/icons/white/Customize.png
napari_signal_selector/icons/white/Forward.png
napari_signal_selector/icons/white/Home.png
napari_signal_selector/icons/white/Pan.png
napari_signal_selector/icons/white/Pan_checked.png
napari_signal_selector/icons/white/Save.png
napari_signal_selector/icons/white/Subplots.png
napari_signal_selector/icons/white/Zoom.png
napari_signal_selector/icons/white/Zoom_checked.png
napari_signal_selector-0.0.6.dist-info/LICENSE
napari_signal_selector-0.0.6.dist-info/METADATA
napari_signal_selector-0.0.6.dist-info/WHEEL
napari_signal_selector-0.0.6.dist-info/entry_points.txt
napari_signal_selector-0.0.6.dist-info/top_level.txt
napari_signal_selector-0.0.6.dist-info/RECORD
