Metadata-Version: 2.1
Name: napari-signal-selector
Version: 0.0.6
Summary: An interactive signal selector for napari, based on matplotlib.
Home-page: https://github.com/zoccoler/napari-signal-selector
Author: Marcelo Leomil Zoccoler
Author-email: marzoccoler@gmail.com
License: BSD-3-Clause
Project-URL: Bug Tracker, https://github.com/zoccoler/napari-signal-selector/issues
Project-URL: Documentation, https://github.com/zoccoler/napari-signal-selector#README.md
Project-URL: Source Code, https://github.com/zoccoler/napari-signal-selector
Project-URL: User Support, https://github.com/zoccoler/napari-signal-selector/issues
Classifier: Development Status :: 2 - Pre-Alpha
Classifier: Framework :: napari
Classifier: Intended Audience :: Developers
Classifier: License :: OSI Approved :: BSD License
Classifier: Operating System :: OS Independent
Classifier: Programming Language :: Python
Classifier: Programming Language :: Python :: 3
Classifier: Programming Language :: Python :: 3 :: Only
Classifier: Programming Language :: Python :: 3.8
Classifier: Programming Language :: Python :: 3.9
Classifier: Programming Language :: Python :: 3.10
Classifier: Programming Language :: Python :: 3.11
Classifier: Topic :: Scientific/Engineering :: Image Processing
Requires-Python: >=3.8
License-File: LICENSE
Requires-Dist: numpy
Requires-Dist: magicgui
Requires-Dist: qtpy
Requires-Dist: cmap
Requires-Dist: nap-plot-tools>=0.1.2
Provides-Extra: testing
Requires-Dist: tox; extra == "testing"
Requires-Dist: pytest; extra == "testing"
Requires-Dist: pytest-cov; extra == "testing"
Requires-Dist: pytest-qt; extra == "testing"
Requires-Dist: napari>=0.4.19; extra == "testing"
Requires-Dist: pyqt5; extra == "testing"
